natpmp/NATPMP.py
natpmp/__init__.py
natpmp/natpmp_client.py
py_natpmp-0.2.5.dist-info/LICENSE
py_natpmp-0.2.5.dist-info/METADATA
py_natpmp-0.2.5.dist-info/WHEEL
py_natpmp-0.2.5.dist-info/entry_points.txt
py_natpmp-0.2.5.dist-info/top_level.txt
py_natpmp-0.2.5.dist-info/zip-safe
py_natpmp-0.2.5.dist-info/RECORD
