Metadata-Version: 2.1
Name: py-natpmp
Version: 0.2.5
Summary: Python classes for interacting with NAT-PMP v0
Home-page: https://github.com/yimingliu/py-natpmp
Author: Yiming Liu
Author-email: yliu@ischool.berkeley.edu
License: BSD
Keywords: NAT-PMP NAT networking port port_forwarding port_mapping AirPort Apple
Classifier: Development Status :: 4 - Beta
Classifier: Intended Audience :: Developers
Classifier: License :: OSI Approved :: BSD License
Classifier: Programming Language :: Python :: 3
Classifier: Programming Language :: Python :: 2.7
Classifier: Topic :: System :: Networking
License-File: LICENSE
